leetscraper/__init__.py
leetscraper/cli.py
leetscraper/driver.py
leetscraper/leetscraper.py
leetscraper/logger.py
leetscraper/scraper.py
leetscraper/utils.py
leetscraper/website.py
leetscraper/drivers/__init__.py
leetscraper/drivers/chromedriver.py
leetscraper/drivers/geckodriver.py
leetscraper/websites/__init__.py
leetscraper/websites/codechef.py
leetscraper/websites/codewars.py
leetscraper/websites/hackerrank.py
leetscraper/websites/leetcode.py
leetscraper/websites/projecteuler.py
leetscraper-2.4.3.dist-info/LICENSE.md
leetscraper-2.4.3.dist-info/METADATA
leetscraper-2.4.3.dist-info/WHEEL
leetscraper-2.4.3.dist-info/entry_points.txt
leetscraper-2.4.3.dist-info/top_level.txt
leetscraper-2.4.3.dist-info/RECORD
