Metadata-Version: 2.1
Name: leetscraper
Version: 2.4.3
Summary: A coding challenge scraper for leetcode, and other websites!
Author: Pavocracy
Author-email: pavocracy@pm.me
Project-URL: Source Code, https://github.com/pavocracy/leetscraper
Project-URL: Issue Tracker, https://github.com/pavocracy/leetscraper/issues
Project-URL: Documentation, https://github.com/Pavocracy/leetscraper/tree/main/docs
Project-URL: Donate, https://github.com/sponsors/Pavocracy
Keywords: python,scraper,automation,selenium
Classifier: Development Status :: 5 - Production/Stable
Classifier: Programming Language :: Python :: 3.7
Classifier: Programming Language :: Python :: 3.8
Classifier: Programming Language :: Python :: 3.9
Classifier: Programming Language :: Python :: 3.10
Classifier: Operating System :: POSIX :: Linux
Classifier: Operating System :: Microsoft :: Windows
Classifier: Operating System :: MacOS
Classifier: License :: OSI Approved :: GNU General Public License v2 (GPLv2)
Requires-Python: >=3.7
License-File: LICENSE.md
Requires-Dist: beautifulsoup4
Requires-Dist: selenium
Requires-Dist: tqdm
Requires-Dist: urllib3
Requires-Dist: webdriver-manager
